approve/__init__.py
approve/models.py
approve/typing.py
approve/utils.py
approve-0.1.1.dist-info/LICENSE
approve-0.1.1.dist-info/METADATA
approve-0.1.1.dist-info/WHEEL
approve-0.1.1.dist-info/top_level.txt
approve-0.1.1.dist-info/RECORD
