Metadata-Version: 2.1
Name: approve
Version: 0.1.1
Summary: A PyTorch Geometric implementation of APPrOVE: Approximate Personalized Propagation Over Varied Edges. APPrOVE extends the well-known personalized PageRank algorithm to heterogeneous graphs (graphs with varied edges).
Author-email: Robert Moerman <robert.william.moerman@gmail.com>
License: MIT
Keywords: deep-learning,pytorch,geometric-deep-learning,graph-neural-networks
Classifier: License :: OSI Approved :: MIT License
Classifier: Programming Language :: Python
Classifier: Programming Language :: Python :: 3.10
Classifier: Programming Language :: Python :: 3.11
Classifier: Programming Language :: Python :: 3 :: Only
Requires-Python: <3.12,>=3.8
License-File: LICENSE
Requires-Dist: torch
Requires-Dist: torch-geometric
Provides-Extra: dev
Requires-Dist: pre-commit ; extra == 'dev'
Requires-Dist: black ; extra == 'dev'
Requires-Dist: flake8 ; extra == 'dev'
Requires-Dist: mypy ; extra == 'dev'
Requires-Dist: isort ; extra == 'dev'
Requires-Dist: jupyter ; extra == 'dev'
Requires-Dist: pytest ; extra == 'dev'
Requires-Dist: pytest-cov ; extra == 'dev'
Provides-Extra: docs
Requires-Dist: sphinx-rtd-theme ; extra == 'docs'
Requires-Dist: toml ; extra == 'docs'
Requires-Dist: types-toml ; extra == 'docs'
